fluvial_particle/FallingParticles.py
fluvial_particle/Helpers.py
fluvial_particle/LarvalParticles.py
fluvial_particle/Particles.py
fluvial_particle/RiverGrid.py
fluvial_particle/Settings.py
fluvial_particle/__init__.py
fluvial_particle-0.0.1.dist-info/LICENSE.md
fluvial_particle-0.0.1.dist-info/WHEEL
fluvial_particle-0.0.1.dist-info/METADATA
fluvial_particle-0.0.1.dist-info/RECORD
