Metadata-Version: 2.1
Name: fluvial-particle
Version: 0.0.1
Summary: Lagrangian particle-tracking for fluvial environments.
Home-page: https://code.usgs.gov/wma/nhgf/fluvparticle
License: LICENSE.md
Author: Richard McDonald
Author-email: rmcd@usgs.gov
Requires-Python: >=3.9,<4.0
Classifier: License :: Other/Proprietary License
Classifier: Programming Language :: Python :: 3
Classifier: Programming Language :: Python :: 3.10
Classifier: Programming Language :: Python :: 3.9
Requires-Dist: h5py (>=3.7.0,<4.0.0)
Requires-Dist: vtk (>=9.1)
Project-URL: Documentation, https://fluvial-particle.readthedocs.io/en/latest/
Project-URL: Repository, https://code.usgs.gov/wma/nhgf/fluvparticle
